COPYING
MANIFEST.in
README.rst
metatools.py
setup.py
test-requires
test_metatools.py
tox.ini
Metatools.egg-info/PKG-INFO
Metatools.egg-info/SOURCES.txt
Metatools.egg-info/dependency_links.txt
Metatools.egg-info/top_level.txt